b9ui/app.py
b9ui/attrs.py
b9ui/base.py
b9ui/components/__init__.py
b9ui/components/body.py
b9ui/components/breadcrumb.py
b9ui/components/button.py
b9ui/components/card.py
b9ui/components/header.py
b9ui/components/image.py
b9ui/components/input.py
b9ui/components/link.py
b9ui/components/navigation_bar.py
b9ui/components/page.py
b9ui/components/product_menu.py
b9ui/components/product_menu_bar.py
b9ui/components/side_panel.py
b9ui/components/table.py
b9ui/components/toast.py
b9ui/html/__init__.py
b9ui/html/svg.py
b9ui/layouts/__init__.py
b9ui/layouts/app_layout.py
b9ui/layouts/project_layout.py
b9ui/layouts/table_editor_layout.py
b9ui/responses.py
b9ui/routing.py
b9ui/types.py
b9ui/utils/__init__.py
b9ui/utils/module_loading.py
b9ui-0.2.0.dist-info/METADATA
b9ui-0.2.0.dist-info/WHEEL
b9ui-0.2.0.dist-info/entry_points.txt
b9ui-0.2.0.dist-info/RECORD
