Metadata-Version: 2.1
Name: b9ui
Version: 0.2.0
Summary: The Next.js like Python framework
License: MIT
Author: Basri
Author-email: h@basri.me
Requires-Python: >=3.12,<4.0
Classifier: License :: OSI Approved :: MIT License
Classifier: Programming Language :: Python :: 3
Classifier: Programming Language :: Python :: 3.12
Requires-Dist: ludic (>=0.4.0,<0.5.0)
Requires-Dist: starlette (>=0.37.2,<0.38.0)
Requires-Dist: typeguard (>=4.2.1,<5.0.0)
Requires-Dist: uvicorn (>=0.29.0,<0.30.0)
